{
  "notes": {
    "403": {
      "vault": {
        "fsPath": ".",
        "selfContained": true,
        "name": "TRWBL"
      },
      "fname": "403",
      "id": "403",
      "title": "This page has not yet sprouted",
      "schemaStub": false,
      "type": "note",
      "updated": 1694909640702,
      "created": 1694909640702,
      "desc": "",
      "links": [],
      "anchors": {},
      "children": [],
      "parent": null,
      "data": {}
    },
    "ycfbd2a8x41gi0smmpufk0o": {
      "id": "ycfbd2a8x41gi0smmpufk0o",
      "title": "The Revolution Will Be Live",
      "desc": "",
      "updated": 1694081432050,
      "created": 1694056545245,
      "custom": {
        "nav_order": 0,
        "permalink": "/"
      },
      "fname": "root",
      "type": "note",
      "vault": {
        "fsPath": ".",
        "selfContained": true,
        "name": "TRWBL"
      },
      "contentHash": "874615ba40d9f49318d28f3e7d67b196",
      "links": [
        {
          "type": "wiki",
          "from": {
            "fname": "root",
            "id": "ycfbd2a8x41gi0smmpufk0o",
            "vaultName": "TRWBL"
          },
          "value": "13-13s",
          "alias": "Yggdrasil",
          "position": {
            "start": {
              "line": 6,
              "column": 84,
              "offset": 397
            },
            "end": {
              "line": 6,
              "column": 104,
              "offset": 417
            },
            "indent": []
          },
          "xvault": false,
          "sameFile": false,
          "to": {
            "fname": "13-13s"
          }
        }
      ],
      "anchors": {},
      "children": [
        "0kpwtvbizo8p5kwm7ut8z4u",
        "ypu9ulohotwrez78fsejofb",
        "t70n32fovw6k11p2ffwejej",
        "877hdm78cgmgv9e33ly0s4r",
        "otfp9itf9ycjy3lf3312gq2",
        "miefx31q2sgnvrka0v040g7",
        "yifbw4yupdr2w4qe4qdh6j2"
      ],
      "parent": null,
      "data": {}
    },
    "yifbw4yupdr2w4qe4qdh6j2": {
      "fname": "daily",
      "stub": true,
      "vault": {
        "fsPath": ".",
        "selfContained": true,
        "name": "TRWBL"
      },
      "schemaStub": false,
      "type": "note",
      "updated": 1694907066088,
      "created": 1694907066088,
      "id": "yifbw4yupdr2w4qe4qdh6j2",
      "desc": "",
      "links": [],
      "anchors": {},
      "children": [
        "3jbdt5q05ucndeybta8a9gs"
      ],
      "parent": "ycfbd2a8x41gi0smmpufk0o",
      "data": {},
      "title": "Daily"
    },
    "3jbdt5q05ucndeybta8a9gs": {
      "fname": "daily.journal",
      "stub": true,
      "vault": {
        "fsPath": ".",
        "selfContained": true,
        "name": "TRWBL"
      },
      "schemaStub": false,
      "type": "note",
      "updated": 1694907066090,
      "created": 1694907066090,
      "id": "3jbdt5q05ucndeybta8a9gs",
      "desc": "",
      "links": [],
      "anchors": {},
      "children": [
        "lps7htrkn6tnf6y54x2yxcl"
      ],
      "parent": "yifbw4yupdr2w4qe4qdh6j2",
      "data": {},
      "title": "Journal"
    },
    "lps7htrkn6tnf6y54x2yxcl": {
      "fname": "daily.journal.2023",
      "stub": true,
      "vault": {
        "fsPath": ".",
        "selfContained": true,
        "name": "TRWBL"
      },
      "schemaStub": false,
      "type": "note",
      "updated": 1694907066090,
      "created": 1694907066090,
      "id": "lps7htrkn6tnf6y54x2yxcl",
      "desc": "",
      "links": [],
      "anchors": {},
      "children": [
        "yca7lekculoe2r1es6huv9x"
      ],
      "parent": "3jbdt5q05ucndeybta8a9gs",
      "data": {},
      "title": "2023"
    },
    "yca7lekculoe2r1es6huv9x": {
      "fname": "daily.journal.2023.09",
      "stub": true,
      "vault": {
        "fsPath": ".",
        "selfContained": true,
        "name": "TRWBL"
      },
      "schemaStub": false,
      "type": "note",
      "updated": 1694907066090,
      "created": 1694907066090,
      "id": "yca7lekculoe2r1es6huv9x",
      "desc": "",
      "links": [],
      "anchors": {},
      "children": [
        "p0w0c1aihdizw86x0uhuq4k"
      ],
      "parent": "lps7htrkn6tnf6y54x2yxcl",
      "data": {},
      "title": "09"
    },
    "p0w0c1aihdizw86x0uhuq4k": {
      "fname": "daily.journal.2023.09.16",
      "vault": {
        "fsPath": ".",
        "selfContained": true,
        "name": "TRWBL"
      },
      "schemaStub": false,
      "type": "note",
      "updated": 1694907066071,
      "created": 1694907066071,
      "id": "p0w0c1aihdizw86x0uhuq4k",
      "desc": "",
      "links": [],
      "anchors": {},
      "children": [],
      "parent": "yca7lekculoe2r1es6huv9x",
      "data": {},
      "title": "2023-09-16",
      "traits": [
        "journalNote"
      ],
      "contentHash": "28811bcf651ff69bf07d4fbda6897b84"
    },
    "miefx31q2sgnvrka0v040g7": {
      "fname": "proposals",
      "stub": true,
      "vault": {
        "fsPath": ".",
        "selfContained": true,
        "name": "TRWBL"
      },
      "schemaStub": false,
      "type": "note",
      "updated": 1694907056025,
      "created": 1694907056025,
      "id": "miefx31q2sgnvrka0v040g7",
      "desc": "",
      "links": [],
      "anchors": {},
      "children": [
        "y8vqiu1cguu7cz8fw08ty95"
      ],
      "parent": "ycfbd2a8x41gi0smmpufk0o",
      "data": {},
      "title": "Proposals"
    },
    "y8vqiu1cguu7cz8fw08ty95": {
      "fname": "proposals.metacartel",
      "stub": true,
      "vault": {
        "fsPath": ".",
        "selfContained": true,
        "name": "TRWBL"
      },
      "schemaStub": false,
      "type": "note",
      "updated": 1694907056026,
      "created": 1694907056026,
      "id": "y8vqiu1cguu7cz8fw08ty95",
      "desc": "",
      "links": [],
      "anchors": {},
      "children": [
        "optc00u1kjkfz656tnghfu7",
        "l8g0vja9faraw5vkigrqqmc"
      ],
      "parent": "miefx31q2sgnvrka0v040g7",
      "data": {},
      "title": "Metacartel"
    },
    "l8g0vja9faraw5vkigrqqmc": {
      "id": "l8g0vja9faraw5vkigrqqmc",
      "title": "№ⅱ",
      "desc": "",
      "updated": 1694071802101,
      "created": 1694070085013,
      "isDir": false,
      "custom": {
        "isDir": false
      },
      "fname": "proposals.metacartel.№ⅱ",
      "type": "note",
      "vault": {
        "fsPath": ".",
        "selfContained": true,
        "name": "TRWBL"
      },
      "contentHash": "c560459cf7ab40953a6100dc19c2d0ec",
      "links": [],
      "anchors": {
        "grant-proposal-for-the-revolution-will-be-live": {
          "type": "header",
          "text": "Grant Proposal for The Revolution Will Be Live",
          "value": "grant-proposal-for-the-revolution-will-be-live",
          "line": 8,
          "column": 0,
          "depth": 1
        },
        "manifesto": {
          "type": "header",
          "text": "Manifesto",
          "value": "manifesto",
          "line": 14,
          "column": 0,
          "depth": 1
        },
        "problem": {
          "type": "header",
          "text": "Problem",
          "value": "problem",
          "line": 44,
          "column": 0,
          "depth": 1
        },
        "solution": {
          "type": "header",
          "text": "Solution",
          "value": "solution",
          "line": 58,
          "column": 0,
          "depth": 1
        },
        "product": {
          "type": "header",
          "text": "Product",
          "value": "product",
          "line": 64,
          "column": 0,
          "depth": 1
        },
        "progress": {
          "type": "header",
          "text": "Progress",
          "value": "progress",
          "line": 74,
          "column": 0,
          "depth": 1
        },
        "differentiation": {
          "type": "header",
          "text": "Differentiation",
          "value": "differentiation",
          "line": 80,
          "column": 0,
          "depth": 1
        },
        "team": {
          "type": "header",
          "text": "Team",
          "value": "team",
          "line": 86,
          "column": 0,
          "depth": 1
        },
        "grant-request": {
          "type": "header",
          "text": "Grant Request",
          "value": "grant-request",
          "line": 90,
          "column": 0,
          "depth": 1
        },
        "help": {
          "type": "header",
          "text": "Help",
          "value": "help",
          "line": 108,
          "column": 0,
          "depth": 1
        }
      },
      "children": [],
      "parent": "y8vqiu1cguu7cz8fw08ty95",
      "data": {}
    },
    "optc00u1kjkfz656tnghfu7": {
      "id": "optc00u1kjkfz656tnghfu7",
      "title": "№ⅰ",
      "desc": "",
      "updated": 1694071758316,
      "created": 1694070085013,
      "isDir": false,
      "custom": {
        "isDir": false
      },
      "fname": "proposals.metacartel.№ⅰ",
      "type": "note",
      "vault": {
        "fsPath": ".",
        "selfContained": true,
        "name": "TRWBL"
      },
      "contentHash": "0f9f7e79cbae3bcdcfbc3c193200a322",
      "links": [],
      "anchors": {
        "grant-proposal-for-mïmis": {
          "type": "header",
          "text": "Grant Proposal for Mïmis",
          "value": "grant-proposal-for-mïmis",
          "line": 8,
          "column": 0,
          "depth": 1
        },
        "manifesto": {
          "type": "header",
          "text": "Manifesto",
          "value": "manifesto",
          "line": 12,
          "column": 0,
          "depth": 1
        },
        "problem": {
          "type": "header",
          "text": "Problem",
          "value": "problem",
          "line": 20,
          "column": 0,
          "depth": 1
        },
        "solution": {
          "type": "header",
          "text": "Solution",
          "value": "solution",
          "line": 34,
          "column": 0,
          "depth": 1
        },
        "product": {
          "type": "header",
          "text": "Product",
          "value": "product",
          "line": 40,
          "column": 0,
          "depth": 1
        },
        "progress": {
          "type": "header",
          "text": "Progress",
          "value": "progress",
          "line": 50,
          "column": 0,
          "depth": 1
        },
        "differentiation": {
          "type": "header",
          "text": "Differentiation",
          "value": "differentiation",
          "line": 58,
          "column": 0,
          "depth": 1
        },
        "team": {
          "type": "header",
          "text": "Team",
          "value": "team",
          "line": 64,
          "column": 0,
          "depth": 1
        },
        "grant-request": {
          "type": "header",
          "text": "Grant Request",
          "value": "grant-request",
          "line": 68,
          "column": 0,
          "depth": 1
        },
        "help": {
          "type": "header",
          "text": "Help",
          "value": "help",
          "line": 86,
          "column": 0,
          "depth": 1
        },
        "additional-resources": {
          "type": "header",
          "text": "Additional Resources",
          "value": "additional-resources",
          "line": 94,
          "column": 0,
          "depth": 1
        }
      },
      "children": [],
      "parent": "y8vqiu1cguu7cz8fw08ty95",
      "data": {}
    },
    "otfp9itf9ycjy3lf3312gq2": {
      "fname": "procedures",
      "stub": true,
      "vault": {
        "fsPath": ".",
        "selfContained": true,
        "name": "TRWBL"
      },
      "schemaStub": false,
      "type": "note",
      "updated": 1694907056016,
      "created": 1694907056016,
      "id": "otfp9itf9ycjy3lf3312gq2",
      "desc": "",
      "links": [],
      "anchors": {},
      "children": [
        "zy2z0cm580djy9r1mv5hfpv",
        "i0pi817k4zm201ladz114om"
      ],
      "parent": "ycfbd2a8x41gi0smmpufk0o",
      "data": {},
      "title": "Procedures"
    },
    "i0pi817k4zm201ladz114om": {
      "id": "i0pi817k4zm201ladz114om",
      "title": "Plugging",
      "desc": "",
      "updated": 1694080305331,
      "created": 1694070085013,
      "isDir": false,
      "custom": {
        "isDir": false
      },
      "fname": "procedures.plugging",
      "type": "note",
      "vault": {
        "fsPath": ".",
        "selfContained": true,
        "name": "TRWBL"
      },
      "contentHash": "33ff4d0d18c1e4f4927ebbc8a02a9aa4",
      "links": [],
      "anchors": {},
      "children": [],
      "parent": "otfp9itf9ycjy3lf3312gq2",
      "data": {}
    },
    "zy2z0cm580djy9r1mv5hfpv": {
      "id": "zy2z0cm580djy9r1mv5hfpv",
      "title": "Party Favors",
      "desc": "",
      "updated": 1694080284419,
      "created": 1694070085013,
      "isDir": false,
      "custom": {
        "isDir": false
      },
      "fname": "procedures.party-favors",
      "type": "note",
      "vault": {
        "fsPath": ".",
        "selfContained": true,
        "name": "TRWBL"
      },
      "contentHash": "6e4e1e3ecea302ca5c6c7fd6fe958e88",
      "links": [],
      "anchors": {},
      "children": [],
      "parent": "otfp9itf9ycjy3lf3312gq2",
      "data": {}
    },
    "877hdm78cgmgv9e33ly0s4r": {
      "id": "877hdm78cgmgv9e33ly0s4r",
      "title": "Warfare",
      "desc": "",
      "updated": 1694080246310,
      "created": 1694070085010,
      "isDir": false,
      "custom": {
        "isDir": false
      },
      "fname": "warfare",
      "type": "note",
      "vault": {
        "fsPath": ".",
        "selfContained": true,
        "name": "TRWBL"
      },
      "contentHash": "73a3c66802df33a923efc5b50c630b65",
      "links": [],
      "anchors": {},
      "children": [],
      "parent": "ycfbd2a8x41gi0smmpufk0o",
      "data": {}
    },
    "t70n32fovw6k11p2ffwejej": {
      "id": "t70n32fovw6k11p2ffwejej",
      "title": "Timeline",
      "desc": "",
      "updated": 1694081168491,
      "created": 1694070085012,
      "isDir": false,
      "nav_order": 10,
      "custom": {
        "isDir": false,
        "nav_order": 10
      },
      "fname": "timeline",
      "type": "note",
      "vault": {
        "fsPath": ".",
        "selfContained": true,
        "name": "TRWBL"
      },
      "contentHash": "2868ef93cd2eaee9e88b3a69118e511a",
      "links": [
        {
          "type": "wiki",
          "from": {
            "fname": "timeline",
            "id": "t70n32fovw6k11p2ffwejej",
            "vaultName": "TRWBL"
          },
          "value": "13-13s.axes.months",
          "alias": "13-sign zodiac",
          "position": {
            "start": {
              "line": 1,
              "column": 96,
              "offset": 95
            },
            "end": {
              "line": 1,
              "column": 133,
              "offset": 132
            },
            "indent": []
          },
          "xvault": false,
          "sameFile": false,
          "to": {
            "fname": "13-13s.axes.months"
          }
        },
        {
          "type": "wiki",
          "from": {
            "fname": "timeline",
            "id": "t70n32fovw6k11p2ffwejej",
            "vaultName": "TRWBL"
          },
          "value": "13-13s",
          "alias": "Thirteen Thirteens",
          "position": {
            "start": {
              "line": 7,
              "column": 12,
              "offset": 273
            },
            "end": {
              "line": 7,
              "column": 41,
              "offset": 302
            },
            "indent": []
          },
          "xvault": false,
          "sameFile": false,
          "to": {
            "fname": "13-13s"
          }
        }
      ],
      "anchors": {},
      "children": [],
      "parent": "ycfbd2a8x41gi0smmpufk0o",
      "data": {}
    },
    "ypu9ulohotwrez78fsejofb": {
      "id": "ypu9ulohotwrez78fsejofb",
      "title": "Funding",
      "desc": "",
      "updated": 1694088293792,
      "created": 1694070085012,
      "nav_order": 20,
      "custom": {
        "nav_order": 20
      },
      "fname": "funding",
      "type": "note",
      "vault": {
        "fsPath": ".",
        "selfContained": true,
        "name": "TRWBL"
      },
      "contentHash": "17a0b847827ca65be0986ba972ce1f4b",
      "links": [],
      "anchors": {},
      "children": [],
      "parent": "ycfbd2a8x41gi0smmpufk0o",
      "data": {}
    },
    "0kpwtvbizo8p5kwm7ut8z4u": {
      "id": "0kpwtvbizo8p5kwm7ut8z4u",
      "title": "13 13s",
      "desc": "",
      "updated": 1694906814311,
      "created": 1694057960761,
      "nav_order": 30,
      "custom": {
        "nav_order": 30
      },
      "fname": "13-13s",
      "type": "note",
      "vault": {
        "fsPath": ".",
        "selfContained": true,
        "name": "TRWBL"
      },
      "contentHash": "1712ceadee90cdca5b6247ca24674ac7",
      "links": [
        {
          "type": "wiki",
          "from": {
            "fname": "13-13s",
            "id": "0kpwtvbizo8p5kwm7ut8z4u",
            "vaultName": "TRWBL"
          },
          "value": "13-13s",
          "alias": "Yggdrasil",
          "position": {
            "start": {
              "line": 8,
              "column": 22,
              "offset": 416
            },
            "end": {
              "line": 8,
              "column": 42,
              "offset": 436
            },
            "indent": []
          },
          "xvault": false,
          "sameFile": false,
          "to": {
            "fname": "13-13s"
          }
        },
        {
          "type": "wiki",
          "from": {
            "fname": "13-13s",
            "id": "0kpwtvbizo8p5kwm7ut8z4u",
            "vaultName": "TRWBL"
          },
          "value": "13-13s.axes.months",
          "alias": "13-sign zodiac",
          "position": {
            "start": {
              "line": 10,
              "column": 160,
              "offset": 622
            },
            "end": {
              "line": 10,
              "column": 197,
              "offset": 659
            },
            "indent": []
          },
          "xvault": false,
          "sameFile": false,
          "to": {
            "fname": "13-13s.axes.months"
          }
        },
        {
          "from": {
            "fname": "13-13s",
            "id": "0kpwtvbizo8p5kwm7ut8z4u",
            "vaultName": "TRWBL"
          },
          "type": "backlink",
          "position": {
            "start": {
              "line": 8,
              "column": 22,
              "offset": 416
            },
            "end": {
              "line": 8,
              "column": 42,
              "offset": 436
            },
            "indent": []
          },
          "value": "13-13s"
        },
        {
          "from": {
            "fname": "timeline",
            "id": "t70n32fovw6k11p2ffwejej",
            "vaultName": "TRWBL"
          },
          "type": "backlink",
          "position": {
            "start": {
              "line": 7,
              "column": 12,
              "offset": 273
            },
            "end": {
              "line": 7,
              "column": 41,
              "offset": 302
            },
            "indent": []
          },
          "value": "13-13s"
        },
        {
          "from": {
            "fname": "root",
            "id": "ycfbd2a8x41gi0smmpufk0o",
            "vaultName": "TRWBL"
          },
          "type": "backlink",
          "position": {
            "start": {
              "line": 6,
              "column": 84,
              "offset": 397
            },
            "end": {
              "line": 6,
              "column": 104,
              "offset": 417
            },
            "indent": []
          },
          "value": "13-13s"
        },
        {
          "from": {
            "fname": "13-13s.conglomerations.enforcement",
            "id": "5zhr7nv3gs8w8wma3llj2yr",
            "vaultName": "TRWBL"
          },
          "type": "backlink",
          "position": {
            "start": {
              "line": 5,
              "column": 4,
              "offset": 53
            },
            "end": {
              "line": 5,
              "column": 29,
              "offset": 78
            },
            "indent": []
          },
          "value": "13-13s"
        }
      ],
      "anchors": {
        "yggdrasil": {
          "type": "header",
          "text": "Yggdrasil",
          "value": "yggdrasil",
          "line": 9,
          "column": 0,
          "depth": 1
        },
        "coordinating-with-the-establishment": {
          "type": "header",
          "text": "Coordinating With The Establishment",
          "value": "coordinating-with-the-establishment",
          "line": 19,
          "column": 0,
          "depth": 2
        }
      },
      "children": [
        "u68x9dgujhgq1ode6yce0qh",
        "1blknwaz6oza7w6k4fyzxxn",
        "n6ox8wstepgiy4dfgob88vv"
      ],
      "parent": "ycfbd2a8x41gi0smmpufk0o",
      "data": {}
    },
    "n6ox8wstepgiy4dfgob88vv": {
      "id": "n6ox8wstepgiy4dfgob88vv",
      "title": "Rules",
      "desc": "",
      "updated": 1694908786187,
      "created": 1694908578759,
      "custom": {},
      "fname": "13-13s.rules",
      "type": "note",
      "vault": {
        "fsPath": ".",
        "selfContained": true,
        "name": "TRWBL"
      },
      "contentHash": "eb85d2f3752d164c115a2fcfe82aefab",
      "links": [],
      "anchors": {},
      "children": [],
      "parent": "0kpwtvbizo8p5kwm7ut8z4u",
      "data": {}
    },
    "1blknwaz6oza7w6k4fyzxxn": {
      "id": "1blknwaz6oza7w6k4fyzxxn",
      "title": "Conglomerations",
      "desc": "",
      "updated": 1694079894546,
      "created": 1694058765003,
      "nav_order": 20,
      "custom": {
        "nav_order": 20
      },
      "fname": "13-13s.conglomerations",
      "type": "note",
      "vault": {
        "fsPath": ".",
        "selfContained": true,
        "name": "TRWBL"
      },
      "contentHash": "1cea443867def9feb2af3c84053d8276",
      "links": [
        {
          "type": "wiki",
          "from": {
            "fname": "13-13s.conglomerations",
            "id": "1blknwaz6oza7w6k4fyzxxn",
            "vaultName": "TRWBL"
          },
          "value": "13-13s.axes",
          "alias": "13 axes",
          "position": {
            "start": {
              "line": 2,
              "column": 58,
              "offset": 58
            },
            "end": {
              "line": 2,
              "column": 81,
              "offset": 81
            },
            "indent": []
          },
          "xvault": false,
          "sameFile": false,
          "to": {
            "fname": "13-13s.axes"
          }
        }
      ],
      "anchors": {},
      "children": [
        "5zhr7nv3gs8w8wma3llj2yr",
        "bxyvpvp4abwhmeb94014cnj",
        "swohjj4oy7pzgx62cxygaca",
        "9wteoqynphzgwdmqmmidazz",
        "5aen46xtcdmcupqm8b1h5w3",
        "pffrzwncoq8j2ygohww07jv"
      ],
      "parent": "0kpwtvbizo8p5kwm7ut8z4u",
      "data": {}
    },
    "pffrzwncoq8j2ygohww07jv": {
      "id": "pffrzwncoq8j2ygohww07jv",
      "title": "“Whites”",
      "desc": "",
      "updated": 1694081448177,
      "created": 1694058943591,
      "nav_order": 60,
      "custom": {
        "nav_order": 60
      },
      "fname": "13-13s.conglomerations.“whites”",
      "type": "note",
      "vault": {
        "fsPath": ".",
        "selfContained": true,
        "name": "TRWBL"
      },
      "contentHash": "9f247f0d6671c2dce55cf2575250bbfe",
      "links": [
        {
          "type": "wiki",
          "from": {
            "fname": "13-13s.conglomerations.“whites”",
            "id": "pffrzwncoq8j2ygohww07jv",
            "vaultName": "TRWBL"
          },
          "value": "13-13s.axes.projects^stay",
          "alias": "Stay",
          "position": {
            "start": {
              "line": 4,
              "column": 16,
              "offset": 51
            },
            "end": {
              "line": 4,
              "column": 50,
              "offset": 85
            },
            "indent": []
          },
          "xvault": false,
          "sameFile": false,
          "to": {
            "fname": "13-13s.axes.projects^stay"
          }
        }
      ],
      "anchors": {},
      "children": [],
      "parent": "1blknwaz6oza7w6k4fyzxxn",
      "data": {}
    },
    "5aen46xtcdmcupqm8b1h5w3": {
      "id": "5aen46xtcdmcupqm8b1h5w3",
      "title": "“Blacks”",
      "desc": "",
      "updated": 1694081450778,
      "created": 1694058896032,
      "nav_order": 50,
      "custom": {
        "nav_order": 50
      },
      "fname": "13-13s.conglomerations.“blacks”",
      "type": "note",
      "vault": {
        "fsPath": ".",
        "selfContained": true,
        "name": "TRWBL"
      },
      "contentHash": "749c156f1f02c8064a69fb9c2aa54191",
      "links": [],
      "anchors": {},
      "children": [],
      "parent": "1blknwaz6oza7w6k4fyzxxn",
      "data": {}
    },
    "9wteoqynphzgwdmqmmidazz": {
      "id": "9wteoqynphzgwdmqmmidazz",
      "title": "The Resistance",
      "desc": "",
      "updated": 1694079490862,
      "created": 1694070085016,
      "nav_order": 20,
      "custom": {
        "nav_order": 20
      },
      "fname": "13-13s.conglomerations.the-resistance",
      "type": "note",
      "vault": {
        "fsPath": ".",
        "selfContained": true,
        "name": "TRWBL"
      },
      "contentHash": "b144293d068384c29cdbf45ea912ad8a",
      "links": [],
      "anchors": {},
      "children": [],
      "parent": "1blknwaz6oza7w6k4fyzxxn",
      "data": {}
    },
    "swohjj4oy7pzgx62cxygaca": {
      "id": "swohjj4oy7pzgx62cxygaca",
      "title": "The Establishment",
      "desc": "",
      "updated": 1694079476850,
      "created": 1694070085016,
      "nav_order": 10,
      "custom": {
        "nav_order": 10
      },
      "fname": "13-13s.conglomerations.the-establishment",
      "type": "note",
      "vault": {
        "fsPath": ".",
        "selfContained": true,
        "name": "TRWBL"
      },
      "contentHash": "8ad7fe50980a3212db6e81f5f6e5a16a",
      "links": [],
      "anchors": {},
      "children": [],
      "parent": "1blknwaz6oza7w6k4fyzxxn",
      "data": {}
    },
    "bxyvpvp4abwhmeb94014cnj": {
      "id": "bxyvpvp4abwhmeb94014cnj",
      "title": "Non Human Life",
      "desc": "",
      "updated": 1694079626599,
      "created": 1694070085016,
      "nav_order": 30,
      "custom": {
        "nav_order": 30
      },
      "fname": "13-13s.conglomerations.non-human-life",
      "type": "note",
      "vault": {
        "fsPath": ".",
        "selfContained": true,
        "name": "TRWBL"
      },
      "contentHash": "7cc359e272f93abb58f4350e366f3687",
      "links": [],
      "anchors": {},
      "children": [],
      "parent": "1blknwaz6oza7w6k4fyzxxn",
      "data": {}
    },
    "5zhr7nv3gs8w8wma3llj2yr": {
      "id": "5zhr7nv3gs8w8wma3llj2yr",
      "title": "Enforcement",
      "desc": "",
      "updated": 1694079831453,
      "created": 1694058990911,
      "nav_order": 40,
      "custom": {
        "nav_order": 40
      },
      "fname": "13-13s.conglomerations.enforcement",
      "type": "note",
      "vault": {
        "fsPath": ".",
        "selfContained": true,
        "name": "TRWBL"
      },
      "contentHash": "f3d01108a37292e83acf14ff511749f7",
      "links": [
        {
          "type": "wiki",
          "from": {
            "fname": "13-13s.conglomerations.enforcement",
            "id": "5zhr7nv3gs8w8wma3llj2yr",
            "vaultName": "TRWBL"
          },
          "value": "13-13s",
          "alias": "aforementioned",
          "position": {
            "start": {
              "line": 5,
              "column": 4,
              "offset": 53
            },
            "end": {
              "line": 5,
              "column": 29,
              "offset": 78
            },
            "indent": []
          },
          "xvault": false,
          "sameFile": false,
          "to": {
            "fname": "13-13s"
          }
        }
      ],
      "anchors": {},
      "children": [],
      "parent": "1blknwaz6oza7w6k4fyzxxn",
      "data": {}
    },
    "u68x9dgujhgq1ode6yce0qh": {
      "id": "u68x9dgujhgq1ode6yce0qh",
      "title": "Axes",
      "desc": "",
      "updated": 1694078817101,
      "created": 1694070085014,
      "nav_order": 10,
      "custom": {
        "nav_order": 10
      },
      "fname": "13-13s.axes",
      "type": "note",
      "vault": {
        "fsPath": ".",
        "selfContained": true,
        "name": "TRWBL"
      },
      "contentHash": "2ab12a5d7160eb9458a9cf4643c60898",
      "links": [
        {
          "from": {
            "fname": "13-13s.conglomerations",
            "id": "1blknwaz6oza7w6k4fyzxxn",
            "vaultName": "TRWBL"
          },
          "type": "backlink",
          "position": {
            "start": {
              "line": 2,
              "column": 58,
              "offset": 58
            },
            "end": {
              "line": 2,
              "column": 81,
              "offset": 81
            },
            "indent": []
          },
          "value": "13-13s.axes"
        }
      ],
      "anchors": {},
      "children": [
        "028i5ev6vm12st09fmriclz",
        "krf1iaj278mz3nyqcywg8pa",
        "plsegjmb7w5pr26udquimph",
        "0xpn6uct46il8jlq46b44xq",
        "9c3w1355o1t5aicclqwi10o",
        "r40billjexhoae4pyxd9dlr",
        "ibxtuq4nuvvglg0luzv15fg",
        "t6dplnemakx4uvjlmr12728",
        "46nefi7al8pvhetye9vg1v2",
        "lm2y34tzmv7uohw20kyly28",
        "b1vftqelffxoswnp70zabq0",
        "nmb42ilobl87ccb41ck9j6l"
      ],
      "parent": "0kpwtvbizo8p5kwm7ut8z4u",
      "data": {}
    },
    "nmb42ilobl87ccb41ck9j6l": {
      "id": "nmb42ilobl87ccb41ck9j6l",
      "title": "Timeframes",
      "desc": "",
      "updated": 1694079414333,
      "created": 1694070085016,
      "nav_order": 100,
      "custom": {
        "nav_order": 100
      },
      "fname": "13-13s.axes.timeframes",
      "type": "note",
      "vault": {
        "fsPath": ".",
        "selfContained": true,
        "name": "TRWBL"
      },
      "contentHash": "12062ae2516c2fab0168ea04ebc7ea42",
      "links": [],
      "anchors": {},
      "children": [],
      "parent": "u68x9dgujhgq1ode6yce0qh",
      "data": {}
    },
    "b1vftqelffxoswnp70zabq0": {
      "id": "b1vftqelffxoswnp70zabq0",
      "title": "Spaces",
      "desc": "",
      "updated": 1694078811520,
      "created": 1694070085016,
      "nav_order": 60,
      "custom": {
        "nav_order": 60
      },
      "fname": "13-13s.axes.spaces",
      "type": "note",
      "vault": {
        "fsPath": ".",
        "selfContained": true,
        "name": "TRWBL"
      },
      "contentHash": "e77b8c5174dd5707e4d5e215ddf2a598",
      "links": [
        {
          "from": {
            "fname": "13-13s.axes.colors.silver",
            "id": "s4rnqejfacu2h5a1i9d88ql",
            "vaultName": "TRWBL"
          },
          "type": "backlink",
          "position": {
            "start": {
              "line": 2,
              "column": 83,
              "offset": 83
            },
            "end": {
              "line": 2,
              "column": 123,
              "offset": 123
            },
            "indent": []
          },
          "value": "13-13s.axes.spaces"
        },
        {
          "from": {
            "fname": "13-13s.axes.colors.silver",
            "id": "s4rnqejfacu2h5a1i9d88ql",
            "vaultName": "TRWBL"
          },
          "type": "backlink",
          "position": {
            "start": {
              "line": 2,
              "column": 100,
              "offset": 100
            },
            "end": {
              "line": 2,
              "column": 140,
              "offset": 140
            },
            "indent": []
          },
          "value": "13-13s.axes.spaces"
        }
      ],
      "anchors": {},
      "children": [],
      "parent": "u68x9dgujhgq1ode6yce0qh",
      "data": {}
    },
    "lm2y34tzmv7uohw20kyly28": {
      "id": "lm2y34tzmv7uohw20kyly28",
      "title": "Realms",
      "desc": "",
      "updated": 1694079434374,
      "created": 1694070085016,
      "nav_order": 110,
      "custom": {
        "nav_order": 110
      },
      "fname": "13-13s.axes.realms",
      "type": "note",
      "vault": {
        "fsPath": ".",
        "selfContained": true,
        "name": "TRWBL"
      },
      "contentHash": "6b32242f34cabc48151cb4e8187e707a",
      "links": [],
      "anchors": {},
      "children": [],
      "parent": "u68x9dgujhgq1ode6yce0qh",
      "data": {}
    },
    "46nefi7al8pvhetye9vg1v2": {
      "id": "46nefi7al8pvhetye9vg1v2",
      "title": "Projects",
      "desc": "",
      "updated": 1694080110764,
      "created": 1694070085015,
      "nav_order": 30,
      "custom": {
        "nav_order": 30
      },
      "fname": "13-13s.axes.projects",
      "type": "note",
      "vault": {
        "fsPath": ".",
        "selfContained": true,
        "name": "TRWBL"
      },
      "contentHash": "6aa00f6b06891ef04117339657d5d8e0",
      "links": [],
      "anchors": {},
      "children": [],
      "parent": "u68x9dgujhgq1ode6yce0qh",
      "data": {}
    },
    "t6dplnemakx4uvjlmr12728": {
      "id": "t6dplnemakx4uvjlmr12728",
      "title": "Needs",
      "desc": "",
      "updated": 1694078511725,
      "created": 1694070085015,
      "nav_order": 20,
      "custom": {
        "nav_order": 20
      },
      "fname": "13-13s.axes.needs",
      "type": "note",
      "vault": {
        "fsPath": ".",
        "selfContained": true,
        "name": "TRWBL"
      },
      "contentHash": "f05f2dc9bf30a203a56cc28cf0d8bd31",
      "links": [],
      "anchors": {},
      "children": [],
      "parent": "u68x9dgujhgq1ode6yce0qh",
      "data": {}
    },
    "ibxtuq4nuvvglg0luzv15fg": {
      "id": "ibxtuq4nuvvglg0luzv15fg",
      "title": "Names",
      "desc": "",
      "updated": 1694079078539,
      "created": 1694070085015,
      "nav_order": 90,
      "custom": {
        "nav_order": 90
      },
      "fname": "13-13s.axes.names",
      "type": "note",
      "vault": {
        "fsPath": ".",
        "selfContained": true,
        "name": "TRWBL"
      },
      "contentHash": "a69275b55574f07a94b01ccc35bf8db8",
      "links": [],
      "anchors": {},
      "children": [],
      "parent": "u68x9dgujhgq1ode6yce0qh",
      "data": {}
    },
    "r40billjexhoae4pyxd9dlr": {
      "id": "r40billjexhoae4pyxd9dlr",
      "title": "Months",
      "desc": "",
      "updated": 1694078526350,
      "created": 1694070085015,
      "nav_order": 40,
      "custom": {
        "nav_order": 40
      },
      "fname": "13-13s.axes.months",
      "type": "note",
      "vault": {
        "fsPath": ".",
        "selfContained": true,
        "name": "TRWBL"
      },
      "contentHash": "98fe4a8e9c41803b3388d7829d51ae43",
      "links": [
        {
          "from": {
            "fname": "13-13s",
            "id": "0kpwtvbizo8p5kwm7ut8z4u",
            "vaultName": "TRWBL"
          },
          "type": "backlink",
          "position": {
            "start": {
              "line": 10,
              "column": 160,
              "offset": 622
            },
            "end": {
              "line": 10,
              "column": 197,
              "offset": 659
            },
            "indent": []
          },
          "value": "13-13s.axes.months"
        },
        {
          "from": {
            "fname": "timeline",
            "id": "t70n32fovw6k11p2ffwejej",
            "vaultName": "TRWBL"
          },
          "type": "backlink",
          "position": {
            "start": {
              "line": 1,
              "column": 96,
              "offset": 95
            },
            "end": {
              "line": 1,
              "column": 133,
              "offset": 132
            },
            "indent": []
          },
          "value": "13-13s.axes.months"
        }
      ],
      "anchors": {},
      "children": [],
      "parent": "u68x9dgujhgq1ode6yce0qh",
      "data": {}
    },
    "9c3w1355o1t5aicclqwi10o": {
      "id": "9c3w1355o1t5aicclqwi10o",
      "title": "Languages",
      "desc": "",
      "updated": 1694088409875,
      "created": 1694070085015,
      "nav_order": 80,
      "custom": {
        "nav_order": 80
      },
      "fname": "13-13s.axes.languages",
      "type": "note",
      "vault": {
        "fsPath": ".",
        "selfContained": true,
        "name": "TRWBL"
      },
      "contentHash": "62b1cbef8ffd5f74a0c3c8c7f8814232",
      "links": [],
      "anchors": {},
      "children": [],
      "parent": "u68x9dgujhgq1ode6yce0qh",
      "data": {}
    },
    "0xpn6uct46il8jlq46b44xq": {
      "id": "0xpn6uct46il8jlq46b44xq",
      "title": "Guilds",
      "desc": "",
      "updated": 1694078944720,
      "created": 1694070085015,
      "nav_order": 70,
      "custom": {
        "nav_order": 70
      },
      "fname": "13-13s.axes.guilds",
      "type": "note",
      "vault": {
        "fsPath": ".",
        "selfContained": true,
        "name": "TRWBL"
      },
      "contentHash": "267ba386475400d6695f0360b4aee247",
      "links": [],
      "anchors": {},
      "children": [],
      "parent": "u68x9dgujhgq1ode6yce0qh",
      "data": {}
    },
    "plsegjmb7w5pr26udquimph": {
      "id": "plsegjmb7w5pr26udquimph",
      "title": "Colors",
      "desc": "",
      "updated": 1694908816322,
      "created": 1694070085015,
      "nav_order": 10,
      "custom": {
        "nav_order": 10
      },
      "fname": "13-13s.axes.colors",
      "type": "note",
      "vault": {
        "fsPath": ".",
        "selfContained": true,
        "name": "TRWBL"
      },
      "contentHash": "f9e3a890c0502326f4f5bed3d7a01ac8",
      "links": [
        {
          "type": "wiki",
          "from": {
            "fname": "13-13s.axes.colors",
            "id": "plsegjmb7w5pr26udquimph",
            "vaultName": "TRWBL"
          },
          "value": "tags.FFFFFF",
          "alias": "#FFFFFF",
          "position": {
            "start": {
              "line": 6,
              "column": 10,
              "offset": 78
            },
            "end": {
              "line": 6,
              "column": 17,
              "offset": 85
            },
            "indent": []
          },
          "xvault": false,
          "to": {
            "fname": "tags.FFFFFF"
          }
        },
        {
          "type": "wiki",
          "from": {
            "fname": "13-13s.axes.colors",
            "id": "plsegjmb7w5pr26udquimph",
            "vaultName": "TRWBL"
          },
          "value": "tags.FFFF00",
          "alias": "#FFFF00",
          "position": {
            "start": {
              "line": 8,
              "column": 11,
              "offset": 112
            },
            "end": {
              "line": 8,
              "column": 18,
              "offset": 119
            },
            "indent": []
          },
          "xvault": false,
          "to": {
            "fname": "tags.FFFF00"
          }
        },
        {
          "type": "wiki",
          "from": {
            "fname": "13-13s.axes.colors",
            "id": "plsegjmb7w5pr26udquimph",
            "vaultName": "TRWBL"
          },
          "value": "tags.FFDF00",
          "alias": "#FFDF00",
          "position": {
            "start": {
              "line": 9,
              "column": 9,
              "offset": 128
            },
            "end": {
              "line": 9,
              "column": 16,
              "offset": 135
            },
            "indent": []
          },
          "xvault": false,
          "to": {
            "fname": "tags.FFDF00"
          }
        },
        {
          "type": "wiki",
          "from": {
            "fname": "13-13s.axes.colors",
            "id": "plsegjmb7w5pr26udquimph",
            "vaultName": "TRWBL"
          },
          "value": "Silver",
          "position": {
            "start": {
              "line": 10,
              "column": 3,
              "offset": 138
            },
            "end": {
              "line": 10,
              "column": 13,
              "offset": 148
            },
            "indent": []
          },
          "xvault": false,
          "sameFile": false,
          "to": {
            "fname": "Silver"
          }
        },
        {
          "type": "wiki",
          "from": {
            "fname": "13-13s.axes.colors",
            "id": "plsegjmb7w5pr26udquimph",
            "vaultName": "TRWBL"
          },
          "value": "tags.C0C0C0",
          "alias": "#C0C0C0",
          "position": {
            "start": {
              "line": 10,
              "column": 15,
              "offset": 150
            },
            "end": {
              "line": 10,
              "column": 22,
              "offset": 157
            },
            "indent": []
          },
          "xvault": false,
          "to": {
            "fname": "tags.C0C0C0"
          }
        },
        {
          "type": "wiki",
          "from": {
            "fname": "13-13s.axes.colors",
            "id": "plsegjmb7w5pr26udquimph",
            "vaultName": "TRWBL"
          },
          "value": "tags.B87333",
          "alias": "#B87333",
          "position": {
            "start": {
              "line": 11,
              "column": 11,
              "offset": 168
            },
            "end": {
              "line": 11,
              "column": 18,
              "offset": 175
            },
            "indent": []
          },
          "xvault": false,
          "to": {
            "fname": "tags.B87333"
          }
        },
        {
          "type": "wiki",
          "from": {
            "fname": "13-13s.axes.colors",
            "id": "plsegjmb7w5pr26udquimph",
            "vaultName": "TRWBL"
          },
          "value": "tags.FF007F",
          "alias": "#FF007F",
          "position": {
            "start": {
              "line": 12,
              "column": 9,
              "offset": 184
            },
            "end": {
              "line": 12,
              "column": 16,
              "offset": 191
            },
            "indent": []
          },
          "xvault": false,
          "to": {
            "fname": "tags.FF007F"
          }
        },
        {
          "type": "wiki",
          "from": {
            "fname": "13-13s.axes.colors",
            "id": "plsegjmb7w5pr26udquimph",
            "vaultName": "TRWBL"
          },
          "value": "tags.FFE5B4",
          "alias": "#FFE5B4",
          "position": {
            "start": {
              "line": 13,
              "column": 10,
              "offset": 201
            },
            "end": {
              "line": 13,
              "column": 17,
              "offset": 208
            },
            "indent": []
          },
          "xvault": false,
          "to": {
            "fname": "tags.FFE5B4"
          }
        }
      ],
      "anchors": {},
      "children": [
        "s4rnqejfacu2h5a1i9d88ql"
      ],
      "parent": "u68x9dgujhgq1ode6yce0qh",
      "data": {}
    },
    "s4rnqejfacu2h5a1i9d88ql": {
      "id": "s4rnqejfacu2h5a1i9d88ql",
      "title": "Silver",
      "desc": "",
      "updated": 1694908540957,
      "created": 1694906839121,
      "custom": {},
      "fname": "13-13s.axes.colors.silver",
      "type": "note",
      "vault": {
        "fsPath": ".",
        "selfContained": true,
        "name": "TRWBL"
      },
      "contentHash": "61784c472249ebf52f3c1130ebca4ad0",
      "links": [
        {
          "type": "wiki",
          "from": {
            "fname": "13-13s.axes.colors.silver",
            "id": "s4rnqejfacu2h5a1i9d88ql",
            "vaultName": "TRWBL"
          },
          "value": "13-13s.rules",
          "alias": "rules",
          "position": {
            "start": {
              "line": 2,
              "column": 36,
              "offset": 36
            },
            "end": {
              "line": 2,
              "column": 58,
              "offset": 58
            },
            "indent": []
          },
          "xvault": false,
          "sameFile": false,
          "to": {
            "fname": "13-13s.rules"
          }
        },
        {
          "type": "wiki",
          "from": {
            "fname": "13-13s.axes.colors.silver",
            "id": "s4rnqejfacu2h5a1i9d88ql",
            "vaultName": "TRWBL"
          },
          "value": "13-13s.axes.spaces",
          "alias": "holders of spaces",
          "position": {
            "start": {
              "line": 2,
              "column": 100,
              "offset": 100
            },
            "end": {
              "line": 2,
              "column": 140,
              "offset": 140
            },
            "indent": []
          },
          "xvault": false,
          "sameFile": false,
          "to": {
            "fname": "13-13s.axes.spaces"
          }
        }
      ],
      "anchors": {},
      "children": [],
      "parent": "plsegjmb7w5pr26udquimph",
      "data": {}
    },
    "krf1iaj278mz3nyqcywg8pa": {
      "id": "krf1iaj278mz3nyqcywg8pa",
      "title": "Captains",
      "desc": "",
      "updated": 1694078759121,
      "created": 1694070085015,
      "nav_order": 50,
      "custom": {
        "nav_order": 50
      },
      "fname": "13-13s.axes.captains",
      "type": "note",
      "vault": {
        "fsPath": ".",
        "selfContained": true,
        "name": "TRWBL"
      },
      "contentHash": "8aedd23a87e06af0d74e6a78893cb069",
      "links": [],
      "anchors": {},
      "children": [],
      "parent": "u68x9dgujhgq1ode6yce0qh",
      "data": {}
    },
    "028i5ev6vm12st09fmriclz": {
      "id": "028i5ev6vm12st09fmriclz",
      "title": "Animals",
      "desc": "",
      "updated": 1694079956563,
      "created": 1694070085015,
      "nav_order": 120,
      "custom": {
        "nav_order": 120
      },
      "fname": "13-13s.axes.animals",
      "type": "note",
      "vault": {
        "fsPath": ".",
        "selfContained": true,
        "name": "TRWBL"
      },
      "contentHash": "f6cebcc64b25fdda88aa7cb117d42c7c",
      "links": [],
      "anchors": {},
      "children": [],
      "parent": "u68x9dgujhgq1ode6yce0qh",
      "data": {}
    }
  },
  "domains": [
    {
      "id": "ycfbd2a8x41gi0smmpufk0o",
      "title": "The Revolution Will Be Live",
      "desc": "",
      "updated": 1694081432050,
      "created": 1694056545245,
      "custom": {
        "nav_order": 0,
        "permalink": "/"
      },
      "fname": "root",
      "type": "note",
      "vault": {
        "fsPath": ".",
        "selfContained": true,
        "name": "TRWBL"
      },
      "contentHash": "874615ba40d9f49318d28f3e7d67b196",
      "links": [
        {
          "type": "wiki",
          "from": {
            "fname": "root",
            "id": "ycfbd2a8x41gi0smmpufk0o",
            "vaultName": "TRWBL"
          },
          "value": "13-13s",
          "alias": "Yggdrasil",
          "position": {
            "start": {
              "line": 6,
              "column": 84,
              "offset": 397
            },
            "end": {
              "line": 6,
              "column": 104,
              "offset": 417
            },
            "indent": []
          },
          "xvault": false,
          "sameFile": false,
          "to": {
            "fname": "13-13s"
          }
        }
      ],
      "anchors": {},
      "children": [
        "0kpwtvbizo8p5kwm7ut8z4u",
        "ypu9ulohotwrez78fsejofb",
        "t70n32fovw6k11p2ffwejej",
        "877hdm78cgmgv9e33ly0s4r",
        "otfp9itf9ycjy3lf3312gq2",
        "miefx31q2sgnvrka0v040g7",
        "yifbw4yupdr2w4qe4qdh6j2"
      ],
      "parent": null,
      "data": {},
      "body": "\n_TRWBL_ is a near-term science fiction story describing the progression from the world of today to a future without homelessness, hunger, or war.\n\nIf such a narrative could be made sufficiently convincing, people might be convinced to participate in the initial steps outlined for bringing the plan to fruition.\n\nThe main vehicle for execution is the creation of an augmented reality game called [[Yggdrasil|13-13s]].\n"
    }
  ],
  "noteIndex": {
    "id": "ycfbd2a8x41gi0smmpufk0o",
    "title": "The Revolution Will Be Live",
    "desc": "",
    "updated": 1694081432050,
    "created": 1694056545245,
    "custom": {
      "nav_order": 0,
      "permalink": "/"
    },
    "fname": "root",
    "type": "note",
    "vault": {
      "fsPath": ".",
      "selfContained": true,
      "name": "TRWBL"
    },
    "contentHash": "874615ba40d9f49318d28f3e7d67b196",
    "links": [
      {
        "type": "wiki",
        "from": {
          "fname": "root",
          "id": "ycfbd2a8x41gi0smmpufk0o",
          "vaultName": "TRWBL"
        },
        "value": "13-13s",
        "alias": "Yggdrasil",
        "position": {
          "start": {
            "line": 6,
            "column": 84,
            "offset": 397
          },
          "end": {
            "line": 6,
            "column": 104,
            "offset": 417
          },
          "indent": []
        },
        "xvault": false,
        "sameFile": false,
        "to": {
          "fname": "13-13s"
        }
      }
    ],
    "anchors": {},
    "children": [
      "0kpwtvbizo8p5kwm7ut8z4u",
      "ypu9ulohotwrez78fsejofb",
      "t70n32fovw6k11p2ffwejej",
      "877hdm78cgmgv9e33ly0s4r",
      "otfp9itf9ycjy3lf3312gq2",
      "miefx31q2sgnvrka0v040g7",
      "yifbw4yupdr2w4qe4qdh6j2"
    ],
    "parent": null,
    "data": {},
    "body": "\n_TRWBL_ is a near-term science fiction story describing the progression from the world of today to a future without homelessness, hunger, or war.\n\nIf such a narrative could be made sufficiently convincing, people might be convinced to participate in the initial steps outlined for bringing the plan to fruition.\n\nThe main vehicle for execution is the creation of an augmented reality game called [[Yggdrasil|13-13s]].\n"
  },
  "vaults": [
    {
      "fsPath": ".",
      "selfContained": true,
      "name": "TRWBL"
    }
  ]
}
